notoecd/__init__.py
notoecd/calls.py
notoecd/datasets.py
notoecd/structure.py
notoecd-0.1.5.dist-info/licenses/LICENSE
notoecd-0.1.5.dist-info/METADATA
notoecd-0.1.5.dist-info/WHEEL
notoecd-0.1.5.dist-info/top_level.txt
notoecd-0.1.5.dist-info/RECORD
