Metadata-Version: 2.4
Name: notoecd
Version: 0.1.5
Summary: Unofficial library for interacting with the OECD Data Explorer through Python.
Author-email: Daniel Vegara Balsa <daniel.vegarabalsa@oecd.org>
License-Expression: MIT
Project-URL: Homepage, https://github.com/dani-37/notoecd
Requires-Python: >=3.10
License-File: LICENSE
Requires-Dist: pandas>=2.0
Requires-Dist: requests>=2.31
Dynamic: license-file
